goodhound/__init__.py
goodhound/__main__.py
goodhound/ghresults.py
goodhound/ghutils.py
goodhound/neodb.py
goodhound/paths.py
goodhound/sqldb.py
goodhound-1.1.2.dist-info/entry_points.txt
goodhound-1.1.2.dist-info/LICENSE
goodhound-1.1.2.dist-info/WHEEL
goodhound-1.1.2.dist-info/METADATA
goodhound-1.1.2.dist-info/RECORD
