Metadata-Version: 2.1
Name: goodhound
Version: 1.1.2
Summary: Attackers think in graphs, defenders think in actions, management think in charts.  GoodHound operationalises Bloodhound by determining the busiest paths to high value targets and creating actionable output to prioritise remediation of attack paths.
Home-page: https://github.com/idnahacks/GoodHound
License: BSD-3-Clause
Author: Andi Morris
Author-email: andi.morris@gmail.com
Requires-Python: >=3.7,<4.0
Classifier: License :: OSI Approved :: BSD License
Classifier: Programming Language :: Python :: 3
Classifier: Programming Language :: Python :: 3.10
Classifier: Programming Language :: Python :: 3.7
Classifier: Programming Language :: Python :: 3.8
Classifier: Programming Language :: Python :: 3.9
Requires-Dist: pandas (==1.3.5)
Requires-Dist: py2neo (==2021.2.3)
Project-URL: Documentation, https://github.com/idnahacks/GoodHound/wiki
Project-URL: Repository, https://github.com/idnahacks/GoodHound
